pyqt_auto_search_bar/__init__.py
pyqt_auto_search_bar/autoSearchBar.py
pyqt_auto_search_bar/ico/__init__.py
pyqt_auto_search_bar/ico/search.svg
pyqt_auto_search_bar/style/__init__.py
pyqt_auto_search_bar/style/lineedit.css
pyqt_auto_search_bar/style/search_bar.css
pyqt_auto_search_bar/style/widget.css
pyqt_auto_search_bar-0.0.11.dist-info/LICENSE
pyqt_auto_search_bar-0.0.11.dist-info/METADATA
pyqt_auto_search_bar-0.0.11.dist-info/WHEEL
pyqt_auto_search_bar-0.0.11.dist-info/top_level.txt
pyqt_auto_search_bar-0.0.11.dist-info/RECORD
